BayesicFitting/__init__.py
BayesicFitting/examples/Bessel-J0-UserModel.ipynb
BayesicFitting/examples/Corona.ipynb
BayesicFitting/examples/CorrelatedErrors.ipynb
BayesicFitting/examples/DryBeans.ipynb
BayesicFitting/examples/HD2039.ipynb
BayesicFitting/examples/Hermite1d-AstropyModel.ipynb
BayesicFitting/examples/Julius-experiment.ipynb
BayesicFitting/examples/Uefa2022.ipynb
BayesicFitting/examples/XandYErrors.ipynb
BayesicFitting/examples/__init__.py
BayesicFitting/examples/alphaComae.ipynb
BayesicFitting/examples/arctanfit.ipynb
BayesicFitting/examples/boyles-law.ipynb
BayesicFitting/examples/chirp1.ipynb
BayesicFitting/examples/chirp2.ipynb
BayesicFitting/examples/coldest.ipynb
BayesicFitting/examples/combifit.ipynb
BayesicFitting/examples/etalonfit.ipynb
BayesicFitting/examples/expfit.ipynb
BayesicFitting/examples/fix-parameters.ipynb
BayesicFitting/examples/gaussfit.ipynb
BayesicFitting/examples/harmonicfit.ipynb
BayesicFitting/examples/modelcomparison.ipynb
BayesicFitting/examples/mrs-fringes.ipynb
BayesicFitting/examples/noise.ipynb
BayesicFitting/examples/noise2.ipynb
BayesicFitting/examples/outliers-2.ipynb
BayesicFitting/examples/outliers.ipynb
BayesicFitting/examples/pulsar.ipynb
BayesicFitting/examples/rainfall.ipynb
BayesicFitting/examples/randommap.ipynb
BayesicFitting/examples/roundtrip.ipynb
BayesicFitting/examples/sealevel.ipynb
BayesicFitting/examples/simplefit.ipynb
BayesicFitting/examples/simplemap.ipynb
BayesicFitting/examples/summerdays.ipynb
BayesicFitting/examples/temperature.ipynb
BayesicFitting/examples/data/Decgf-Methanol-1-5.fits
BayesicFitting/examples/data/Dry_Bean_Dataset.csv
BayesicFitting/examples/data/ElfStedenIJs.csv
BayesicFitting/examples/data/HD2039-Tinney.dat
BayesicFitting/examples/data/HTRU.csv
BayesicFitting/examples/data/MRSdata.csv
BayesicFitting/examples/data/MaasTemp.csv
BayesicFitting/examples/data/NationsLeague-2022.txt
BayesicFitting/examples/data/Qualifiers-2022.txt
BayesicFitting/examples/data/RijnTemp.csv
bayesicfitting-3.2.5.dist-info/licenses/LICENSE
bayesicfitting-3.2.5.dist-info/METADATA
bayesicfitting-3.2.5.dist-info/WHEEL
bayesicfitting-3.2.5.dist-info/top_level.txt
bayesicfitting-3.2.5.dist-info/RECORD
