Metadata-Version: 2.4
Name: BayesicFitting
Version: 3.2.5
Summary: A Toolbox for Bayesian Fitting and Evidence Calculation
Author-email: Do Kester <dokester@home.nl>
License-Expression: GPL-3.0-or-later
Keywords: Bayesian,modeling,evidence,statistics,analysis,regression,inference,optimization,nested sampling,fitting
Classifier: Development Status :: 4 - Beta
Classifier: Programming Language :: Python :: 3
Classifier: Operating System :: OS Independent
Classifier: Intended Audience :: Science/Research
Classifier: Topic :: Scientific/Engineering
Requires-Python: >=3.8
License-File: LICENSE
Requires-Dist: numpy>=1.9
Requires-Dist: matplotlib>=2.0
Requires-Dist: scipy>=1.0
Requires-Dist: astropy>=2.0
Requires-Dist: future
Dynamic: license-file
